LICENSE
README.md
setup.py
Diffuzz.egg-info/PKG-INFO
Diffuzz.egg-info/SOURCES.txt
Diffuzz.egg-info/dependency_links.txt
Diffuzz.egg-info/requires.txt
Diffuzz.egg-info/top_level.txt
diffuzz/__init__.py
diffuzz/diffuzz
diffuzz/main.py
diffuzz/options.py
diffuzz/scan_types/__init__.py
diffuzz/scan_types/battering_ram.py
diffuzz/scan_types/cluster_bomb.py
diffuzz/scan_types/dual_battering_ram.py
diffuzz/scan_types/dual_cluster_bomb.py
diffuzz/scan_types/dual_pitch_fork.py
diffuzz/scan_types/dual_sniper.py
diffuzz/scan_types/pitch_fork.py
diffuzz/scan_types/sniper.py