Metadata-Version: 2.4
Name: Diffuzz
Version: 1.0.1
Summary: Web fuzzer finding differences based on response diffing
Author: William
Author-email: william.kristof@gmail.com
License-File: LICENSE
Requires-Dist: requests
Requires-Dist: httpdiff
Requires-Dist: httpinsert
Dynamic: author
Dynamic: author-email
Dynamic: description
Dynamic: description-content-type
Dynamic: license-file
Dynamic: requires-dist
Dynamic: summary
